nameko_sematext/__init__.py
nameko_sematext/logger.py
nameko_sematext_logger-0.0.1.dist-info/METADATA
nameko_sematext_logger-0.0.1.dist-info/WHEEL
nameko_sematext_logger-0.0.1.dist-info/top_level.txt
nameko_sematext_logger-0.0.1.dist-info/zip-safe
nameko_sematext_logger-0.0.1.dist-info/RECORD
