Metadata-Version: 2.1
Name: nameko-sematext-logger
Version: 0.0.1
Summary: Nameko extension for sematext logging
Home-page: https://github.com/raman-grit/nameko-sematext-logger
Author: Raman Damodar Shahdadpuri
Author-email: raman@gritfirst.com
License: GritFirst
Platform: UNKNOWN
Requires-Dist: nameko (>=2.7.0)
